<Properties StartupConfiguration="{9A4A51FB-04FC-4B87-863C-4396192699BB}|https" GitUserInfo="UsingGIT">
  <MultiItemStartupConfigurations />
  <MonoDevelop.Ide.ItemProperties.Assign1 PreferredExecutionTarget="/Applications/Brave Browser.app" />
  <MonoDevelop.Ide.DebuggingService.PinnedWatches />
  <MonoDevelop.Ide.DebuggingService.Breakpoints>
    <BreakpointStore />
  </MonoDevelop.Ide.DebuggingService.Breakpoints>
  <MonoDevelop.Ide.Workbench ActiveDocument="Views/Booking/CreateFlight.cshtml">
    <Files>
      <File FileName="Controllers/BookingController.cs" Line="83" Column="34" />
      <File FileName="Views/Booking/CreateFlight.cshtml" Line="54" Column="1" />
    </Files>
    <Pads>
      <Pad Id="ProjectPad">
        <State name="__root__">
          <Node name="Assign1">
            <Node name="Assign1">
              <Node name="Controllers" expanded="True" />
              <Node name="Migrations" expanded="True">
                <Node name="20240222221941_UpdateBookingWithServiceFields.cs" expanded="True" />
              </Node>
              <Node name="Models" expanded="True" />
              <Node name="Views" expanded="True">
                <Node name="Booking" expanded="True" />
              </Node>
            </Node>
          </Node>
        </State>
      </Pad>
    </Pads>
  </MonoDevelop.Ide.Workbench>
  <MonoDevelop.Ide.Workspace ActiveConfiguration="Debug" />
</Properties>